{"stats":{"minecraft:killed":{"minecraft:sheep":2},"minecraft:picked_up":{"minecraft:diamond_chestplate":1,"minecraft:diamond_leggings":1,"minecraft:diamond_sword":1,"minecraft:diamond_boots":1,"minecraft:golden_apple":22,"minecraft:light_gray_wool":1,"minecraft:diamond_helmet":1,"minecraft:mutton":4,"minecraft:white_wool":1},"minecraft:dropped":{"minecraft:light_gray_wool":1,"minecraft:mutton":4,"minecraft:white_wool":1},"minecraft:used":{"minecraft:netherite_sword":6,"minecraft:diamond_chestplate":1,"minecraft:golden_apple":3,"minecraft:diamond_sword":1,"minecraft:diamond_boots":1,"minecraft:firework_rocket":68,"minecraft:grass_block":14,"minecraft:elytra":1,"minecraft:diamond_helmet":1,"minecraft:diamond_leggings":1},"minecraft:mined":{"minecraft:grass":22,"minecraft:tall_grass":5},"minecraft:custom":{"minecraft:time_since_rest":21846,"minecraft:crouch_one_cm":4082,"minecraft:play_time":21846,"minecraft:sprint_one_cm":15361,"minecraft:damage_taken":253,"minecraft:damage_absorbed":32,"minecraft:walk_one_cm":16175,"minecraft:sneak_time":973,"minecraft:walk_under_water_one_cm":181,"minecraft:mob_kills":2,"minecraft:drop":4,"minecraft:aviate_one_cm":811467,"minecraft:jump":182,"minecraft:damage_dealt":843,"minecraft:leave_game":3,"minecraft:time_since_death":21846,"minecraft:walk_on_water_one_cm":584,"minecraft:total_world_time":21846,"minecraft:climb_one_cm":315,"minecraft:fall_one_cm":5940,"minecraft:fly_one_cm":176914}},"DataVersion":3465}